pynsupdate/__init__.py
pynsupdate/pynsupdate.py
pynsupdate-0.6.0.dist-info/licenses/LICENSE
pynsupdate-0.6.0.dist-info/METADATA
pynsupdate-0.6.0.dist-info/WHEEL
pynsupdate-0.6.0.dist-info/entry_points.txt
pynsupdate-0.6.0.dist-info/top_level.txt
pynsupdate-0.6.0.dist-info/RECORD
