Metadata-Version: 2.4
Name: pynsupdate
Version: 0.6.0
Summary: A python wrapper to Dynamically update DNS using nsupdate
Author: Júlio Dantas
License: MIT License
Project-URL: Homepage, https://github.com/jldantas/pynsupdate
Project-URL: Issues, https://github.com/jldantas/pynsupdate/issues
Project-URL: Repository, https://github.com/jldantas/pynsupdat.git
Classifier: Development Status :: 5 - Production/Stable
Classifier: Environment :: Console
Classifier: Intended Audience :: Other Audience
Classifier: Intended Audience :: Information Technology
Classifier: License :: OSI Approved :: MIT License
Classifier: Operating System :: POSIX
Classifier: Programming Language :: Python :: 3.10
Classifier: Topic :: Internet :: Name Service (DNS)
Requires-Python: >=3.10
License-File: LICENSE
Requires-Dist: psutil>=6.1.0
Dynamic: license-file
